[
    {
        "id": 6375829,
        "sku": "WB-7491559398",
        "article": "Джоггеры",
        "buyer": "Петр В.",
        "price": "4774 ₽",
        "status": "Новый",
        "date": "13.07 11:45"
    },
    {
        "id": 6306374,
        "sku": "WB-3755537758",
        "article": "Футболка Oversize",
        "buyer": "Иван И.",
        "price": "4664 ₽",
        "status": "Новый",
        "date": "13.07 11:45"
    },
    {
        "id": 4557555,
        "sku": "WB-3604713097",
        "article": "Кепка Logo",
        "buyer": "Петр В.",
        "price": "1280 ₽",
        "status": "Новый",
        "date": "13.07 11:45"
    }
]