[
    {
        "id": 8760411,
        "sku": "WB-5081588870",
        "article": "Футболка Oversize",
        "buyer": "Анна С.",
        "price": "2524 ₽",
        "status": "Новый",
        "date": "15.07 18:43"
    },
    {
        "id": 8675490,
        "sku": "WB-5425073240",
        "article": "Джоггеры",
        "buyer": "Петр В.",
        "price": "4238 ₽",
        "status": "Новый",
        "date": "15.07 18:43"
    },
    {
        "id": 1274770,
        "sku": "WB-6803059813",
        "article": "Джоггеры",
        "buyer": "Петр В.",
        "price": "4734 ₽",
        "status": "Новый",
        "date": "15.07 18:43"
    }
]